ckanext/__init__.py
ckanext/iso19115/__init__.py
ckanext/iso19115/builder.py
ckanext/iso19115/cli.py
ckanext/iso19115/config_declaration.yaml
ckanext/iso19115/formatter.py
ckanext/iso19115/helpers.py
ckanext/iso19115/interfaces.py
ckanext/iso19115/plugin.py
ckanext/iso19115/presets.yaml
ckanext/iso19115/utils.py
ckanext/iso19115/views.py
ckanext/iso19115/assets/iso19115-script.js
ckanext/iso19115/assets/iso19115-style.css
ckanext/iso19115/assets/webassets.yml
ckanext/iso19115/converter/__init__.py
ckanext/iso19115/converter/helpers.py
ckanext/iso19115/logic/__init__.py
ckanext/iso19115/logic/action.py
ckanext/iso19115/namespaces/19110/fcc/1.0/abstract.xsd
ckanext/iso19115/namespaces/19110/fcc/1.0/fcc.xsd
ckanext/iso19115/namespaces/19110/gfc/1.1/exampleInstance.xml
ckanext/iso19115/namespaces/19110/gfc/1.1/featureCatalogue.xsd
ckanext/iso19115/namespaces/19110/gfc/1.1/gfc.xsd
ckanext/iso19115/namespaces/19115/-2/gmi/1.0/acquisitionInformation.xsd
ckanext/iso19115/namespaces/19115/-2/gmi/1.0/contentInformation.xsd
ckanext/iso19115/namespaces/19115/-2/gmi/1.0/dataQualityInformation.xsd
ckanext/iso19115/namespaces/19115/-2/gmi/1.0/gmi.xsd
ckanext/iso19115/namespaces/19115/-2/gmi/1.0/metadataEntitySet.xsd
ckanext/iso19115/namespaces/19115/-2/gmi/1.0/spatialRepresentationInformation.xsd
ckanext/iso19115/namespaces/19115/-3/cat/1.0/cat.xsd
ckanext/iso19115/namespaces/19115/-3/cat/1.0/catalogues.xsd
ckanext/iso19115/namespaces/19115/-3/cat/1.0/codelistItem.xsd
ckanext/iso19115/namespaces/19115/-3/cat/1.0/crsItem.xsd
ckanext/iso19115/namespaces/19115/-3/cat/1.0/uomItem.xsd
ckanext/iso19115/namespaces/19115/-3/cit/1.0/cit.xsd
ckanext/iso19115/namespaces/19115/-3/cit/1.0/cit_invalid.xml
ckanext/iso19115/namespaces/19115/-3/cit/1.0/cit_valid.xml
ckanext/iso19115/namespaces/19115/-3/cit/1.0/citation.xsd
ckanext/iso19115/namespaces/19115/-3/cit/1.0/codelists.xml
ckanext/iso19115/namespaces/19115/-3/cit/2.0/cit.xsd
ckanext/iso19115/namespaces/19115/-3/cit/2.0/cit_revised.xml
ckanext_iso19115-0.2.1.dist-info/LICENSE
ckanext_iso19115-0.2.1.dist-info/METADATA
ckanext_iso19115-0.2.1.dist-info/WHEEL
ckanext_iso19115-0.2.1.dist-info/entry_points.txt
ckanext_iso19115-0.2.1.dist-info/top_level.txt
ckanext_iso19115-0.2.1.dist-info/RECORD
